snakeviz/__init__.py
snakeviz/__main__.py
snakeviz/cli.py
snakeviz/ipymagic.py
snakeviz/main.py
snakeviz/stats.py
snakeviz/static/drawsvg.js
snakeviz/static/favicon.ico
snakeviz/static/snakeviz.css
snakeviz/static/snakeviz.js
snakeviz/static/images/sort_asc.png
snakeviz/static/images/sort_both.png
snakeviz/static/images/sort_desc.png
snakeviz/static/vendor/d3.v3.min.js
snakeviz/static/vendor/immutable.min.js
snakeviz/static/vendor/jquery-3.2.1.min.js
snakeviz/static/vendor/jquery.dataTables.min.css
snakeviz/static/vendor/jquery.dataTables.min.js
snakeviz/static/vendor/lodash.min.js
snakeviz/templates/dir.html
snakeviz/templates/viz.html
snakeviz-2.2.2.dist-info/LICENSE.txt
snakeviz-2.2.2.dist-info/METADATA
snakeviz-2.2.2.dist-info/WHEEL
snakeviz-2.2.2.dist-info/entry_points.txt
snakeviz-2.2.2.dist-info/top_level.txt
snakeviz-2.2.2.dist-info/RECORD
