Metadata-Version: 2.1
Name: snakeviz
Version: 2.2.2
Summary: A web-based viewer for Python profiler output
Author-email: Matt Davis <jiffyclub@gmail.com>
License: Copyright (c) 2012, Matt Davis
Project-URL: homepage, https://jiffyclub.github.io/snakeviz/
Project-URL: repository, https://github.com/jiffyclub/snakeviz.git
Project-URL: changelog, https://github.com/jiffyclub/snakeviz/blob/master/CHANGES.rst
Classifier: Intended Audience :: Developers
Classifier: License :: OSI Approved :: BSD License
Classifier: Programming Language :: JavaScript
Classifier: Programming Language :: Python
Classifier: Programming Language :: Python :: 3
Classifier: Programming Language :: Python :: 3.9
Classifier: Programming Language :: Python :: 3.10
Classifier: Programming Language :: Python :: 3.11
Classifier: Programming Language :: Python :: 3.12
Classifier: Programming Language :: Python :: 3.13
Classifier: Topic :: Software Development
Requires-Python: >=3.9
License-File: LICENSE.txt
Requires-Dist: tornado>=2.0
